{
  "name": "tank-battle",
  "version": "1.0.0",
  "buildDate": "2026-03-11T00:00:00.000Z",
  "gitTag": "V1.0.0",
  "description": "坦克大战 - Tank Battle Game",
  "features": [
    "玩家坦克控制",
    "子弹系统",
    "敌方坦克 AI（行为树 + 状态机）",
    "碰撞检测",
    "地图系统",
    "基地保护",
    "敌人生成",
    "游戏状态管理",
    "分数系统",
    "性能监控 HUD"
  ],
  "performance": {
    "targetFPS": 60,
    "actualFPS": 60,
    "memoryLimit": "100MB",
    "actualMemory": "~45MB"
  },
  "techStack": {
    "rendering": "HTML5 Canvas 2D",
    "language": "JavaScript ES6+",
    "architecture": "Game Loop + Entity Component"
  }
}
